llama_index_extra_llm/__init__.py
llama_index_extra_llm/deepseek.py
llama_index_extra_llm-0.0.7.dist-info/LICENSE
llama_index_extra_llm-0.0.7.dist-info/METADATA
llama_index_extra_llm-0.0.7.dist-info/WHEEL
llama_index_extra_llm-0.0.7.dist-info/top_level.txt
llama_index_extra_llm-0.0.7.dist-info/RECORD
