Metadata-Version: 2.1
Name: llama-index-extra-llm
Version: 0.0.7
Summary: Just a simple extension for LlamaIndex for better apply some llm such as DeepSeek.
Home-page: https://github.com/zeuscsc/llama_index_extra_llm.git
Author: Zeus Chiu
Author-email: zeuscsc@gmail.com
License: MIT
Classifier: License :: OSI Approved :: MIT License
Classifier: Programming Language :: Python
Classifier: Programming Language :: Python :: 3
Classifier: Programming Language :: Python :: 3.6
Classifier: Programming Language :: Python :: Implementation :: CPython
Classifier: Programming Language :: Python :: Implementation :: PyPy
Requires-Python: >=3.9.0
License-File: LICENSE
Requires-Dist: transformers ==4.36.2
Requires-Dist: llama-index ==0.9.13
Requires-Dist: accelerate ==0.25.0
Requires-Dist: pypdf ==3.17.4
Requires-Dist: pydantic ==1.10.11
Requires-Dist: bitsandbytes ==0.39
